requestium/__init__.py
requestium/requestium.py
requestium/requestium_mixin.py
requestium/requestium_response.py
requestium/requestium_session.py
requestium-0.5.1.dist-info/licenses/LICENSE
requestium-0.5.1.dist-info/METADATA
requestium-0.5.1.dist-info/WHEEL
requestium-0.5.1.dist-info/top_level.txt
requestium-0.5.1.dist-info/RECORD
