Metadata-Version: 2.4
Name: requestium
Version: 0.5.1
Author-email: Joaquin Alori <joaquin@tryolabs.com>
Maintainer-email: Judson Neer <jkudson.neer@gmail.com>
License: BSD 3-Clause License
Project-URL: source, https://github.com/tryolabs/requestium
Project-URL: download, https://pypi.org/project/requestium/#files
Project-URL: issues, https://github.com/tryolabs/requestium/issues
Classifier: Development Status :: 4 - Beta
Classifier: Intended Audience :: Developers
Classifier: License :: OSI Approved :: BSD License
Classifier: Programming Language :: Python :: 3.10
Classifier: Programming Language :: Python :: 3.11
Classifier: Programming Language :: Python :: 3.12
Classifier: Programming Language :: Python :: 3.13
Classifier: Programming Language :: Python :: 3.14
Classifier: Natural Language :: English
Classifier: Operating System :: MacOS
Classifier: Operating System :: Microsoft :: Windows
Classifier: Operating System :: POSIX
Classifier: Operating System :: OS Independent
Classifier: Environment :: Web Environment
Classifier: Programming Language :: Python :: Implementation :: CPython
Classifier: Topic :: Software Development :: Libraries :: Python Modules
Classifier: Topic :: Software Development :: Testing
Requires-Python: >=3.10
License-File: LICENSE
Requires-Dist: parsel>=1.7
Requires-Dist: requests>=2.27
Requires-Dist: selenium>=4.32
Requires-Dist: tldextract>=5.3
Provides-Extra: dev
Requires-Dist: bandit[sarif]==1.9.2; extra == "dev"
Requires-Dist: mypy==1.19.1; extra == "dev"
Requires-Dist: pre-commit~=4.5.0; extra == "dev"
Requires-Dist: pytest-cov~=7.0.0; extra == "dev"
Requires-Dist: pytest-xdist~=3.8.0; extra == "dev"
Requires-Dist: pytest~=9.0.0; extra == "dev"
Requires-Dist: ruff==0.14.11; extra == "dev"
Requires-Dist: ssort==0.16.0; extra == "dev"
Requires-Dist: types-requests==2.32.4.20260107; extra == "dev"
Dynamic: license-file
